filebridging/__init__.py
filebridging/client.py
filebridging/create_certificate.py
filebridging/old_config.py
filebridging/server.py
filebridging/utilities.py
filebridging-0.0.9.dist-info/METADATA
filebridging-0.0.9.dist-info/WHEEL
filebridging-0.0.9.dist-info/top_level.txt
filebridging-0.0.9.dist-info/RECORD
