Metadata-Version: 2.1
Name: filebridging
Version: 0.0.9
Summary: Share files via a bridge server using TCP over SSL and end-to-end encryption.
Home-page: https://gogs.davte.it/davte/filebridging
Author: Davide Testa
Author-email: davide@davte.it
License: GNU General Public License v3.0
Keywords: file share tcp ssl tls end-to-end encryption python asyncio async
Platform: any
Classifier: Development Status :: 5 - Production/Stable
Classifier: Environment :: Console
Classifier: Framework :: AsyncIO
Classifier: Intended Audience :: End Users/Desktop
Classifier: License :: OSI Approved :: GNU General Public License v3 (GPLv3)
Classifier: Natural Language :: English
Classifier: Operating System :: OS Independent
Classifier: Programming Language :: Python :: 3 :: Only
Classifier: Topic :: Communications :: File Sharing
